chisel4ml/__init__.py
chisel4ml/_version.py
chisel4ml/accelerator.py
chisel4ml/chisel4ml_server.py
chisel4ml/circuit.py
chisel4ml/generate.py
chisel4ml/py.typed
chisel4ml/qtensor.py
chisel4ml/transform.py
chisel4ml/lbir/__init__.py
chisel4ml/lbir/datatype_pb2.py
chisel4ml/lbir/datatype_pb2_grpc.py
chisel4ml/lbir/lbir_pb2.py
chisel4ml/lbir/lbir_pb2_grpc.py
chisel4ml/lbir/qtensor_pb2.py
chisel4ml/lbir/qtensor_pb2_grpc.py
chisel4ml/lbir/services_pb2.py
chisel4ml/lbir/services_pb2_grpc.py
chisel4ml/lbir/scalapb/scalapb_pb2.py
chisel4ml/lbir/scalapb/scalapb_pb2_grpc.py
chisel4ml/preprocess/__init__.py
chisel4ml/preprocess/fft_qonnx_op.py
chisel4ml/preprocess/fft_torch_op.py
chisel4ml/preprocess/lmfe_qonnx_op.py
chisel4ml/preprocess/lmfe_torch_op.py
chisel4ml/transforms/__init__.py
chisel4ml/transforms/extract_quantized_bias.py
chisel4ml/transforms/numpy_transforms.py
chisel4ml/transforms/qonnx_to_lbir.py
chisel4ml/transforms/qonnx_utils.py
chisel4ml/transforms/transform_conv.py
chisel4ml/transforms/transform_fftreal.py
chisel4ml/transforms/transform_lmfe.py
chisel4ml/transforms/transform_matmul.py
chisel4ml/transforms/transform_maxpool.py
chisel4ml-0.3.6.dist-info/AUTHORS
chisel4ml-0.3.6.dist-info/LICENSE
chisel4ml-0.3.6.dist-info/METADATA
chisel4ml-0.3.6.dist-info/WHEEL
chisel4ml-0.3.6.dist-info/top_level.txt
chisel4ml-0.3.6.dist-info/RECORD
