Metadata-Version: 2.2
Name: chisel4ml
Version: 0.3.6
Summary: A Chisel based hardware generation library for deeply quantized neural networks.
Author-email: Jure Vreca <jure.vreca@ijs.si>
License:                                  Apache License
Project-URL: Repository, https://github.com/cs-jsi/chisel4ml
Keywords: Chisel,FPGA,quantized neural networks
Classifier: Topic :: Scientific/Engineering :: Artificial Intelligence
Classifier: Intended Audience :: Science/Research
Classifier: Operating System :: OS Independent
Requires-Python: >=3.8
License-File: LICENSE
License-File: AUTHORS
Requires-Dist: qonnx
Requires-Dist: onnxoptimizer
Requires-Dist: ortools
Requires-Dist: grpcio>1.0.0
Provides-Extra: dev
Requires-Dist: tox<4; extra == "dev"
Requires-Dist: tox-run-before; extra == "dev"
Requires-Dist: pytest<8; extra == "dev"
Requires-Dist: pytest-xdist; extra == "dev"
Requires-Dist: grpcio-tools; extra == "dev"
Requires-Dist: pre-commit; extra == "dev"
Requires-Dist: brevitas; extra == "dev"
Provides-Extra: audio
Requires-Dist: tensorflow-datasets; extra == "audio"
Requires-Dist: librosa; extra == "audio"
